botorch/__init__.py
botorch/cross_validation.py
botorch/fit.py
botorch/logging.py
botorch/py.typed
botorch/settings.py
botorch/version.py
botorch/acquisition/__init__.py
botorch/acquisition/acquisition.py
botorch/acquisition/active_learning.py
botorch/acquisition/analytic.py
botorch/acquisition/bayesian_active_learning.py
botorch/acquisition/cached_cholesky.py
botorch/acquisition/cost_aware.py
botorch/acquisition/decoupled.py
botorch/acquisition/factory.py
botorch/acquisition/fixed_feature.py
botorch/acquisition/input_constructors.py
botorch/acquisition/joint_entropy_search.py
botorch/acquisition/knowledge_gradient.py
botorch/acquisition/logei.py
botorch/acquisition/max_value_entropy_search.py
botorch/acquisition/monte_carlo.py
botorch/acquisition/multi_step_lookahead.py
botorch/acquisition/multioutput_acquisition.py
botorch/acquisition/objective.py
botorch/acquisition/penalized.py
botorch/acquisition/predictive_entropy_search.py
botorch/acquisition/preference.py
botorch/acquisition/prior_guided.py
botorch/acquisition/proximal.py
botorch/acquisition/risk_measures.py
botorch/acquisition/thompson_sampling.py
botorch/acquisition/utils.py
botorch/acquisition/multi_objective/__init__.py
botorch/acquisition/multi_objective/analytic.py
botorch/acquisition/multi_objective/base.py
botorch/acquisition/multi_objective/hypervolume_knowledge_gradient.py
botorch/acquisition/multi_objective/joint_entropy_search.py
botorch/acquisition/multi_objective/logei.py
botorch/acquisition/multi_objective/max_value_entropy_search.py
botorch/acquisition/multi_objective/monte_carlo.py
botorch/acquisition/multi_objective/multi_fidelity.py
botorch/acquisition/multi_objective/multi_output_risk_measures.py
botorch/acquisition/multi_objective/objective.py
botorch/acquisition/multi_objective/parego.py
botorch/acquisition/multi_objective/predictive_entropy_search.py
botorch/acquisition/multi_objective/utils.py
botorch/exceptions/__init__.py
botorch/exceptions/errors.py
botorch/exceptions/warnings.py
botorch-0.16.0.dist-info/licenses/LICENSE
botorch-0.16.0.dist-info/METADATA
botorch-0.16.0.dist-info/WHEEL
botorch-0.16.0.dist-info/top_level.txt
botorch-0.16.0.dist-info/RECORD
