Metadata-Version: 2.4
Name: botorch
Version: 0.16.0
Summary: Bayesian Optimization in PyTorch
Author: Meta Platforms, Inc.
License-Expression: MIT
Project-URL: Homepage, https://botorch.org
Project-URL: Documentation, https://botorch.org
Project-URL: Repository, https://github.com/meta-pytorch/botorch
Keywords: Bayesian optimization,PyTorch
Classifier: Development Status :: 4 - Beta
Classifier: Programming Language :: Python :: 3 :: Only
Classifier: Topic :: Scientific/Engineering
Classifier: Intended Audience :: Science/Research
Classifier: Intended Audience :: Developers
Requires-Python: >=3.10
License-File: LICENSE
Requires-Dist: typing_extensions
Requires-Dist: pyre_extensions
Requires-Dist: gpytorch>=1.14.2
Requires-Dist: linear_operator>=0.6
Requires-Dist: torch>=2.0.1
Requires-Dist: pyro-ppl>=1.8.4
Requires-Dist: scipy
Requires-Dist: multipledispatch
Requires-Dist: threadpoolctl
Provides-Extra: pymoo
Requires-Dist: pymoo; extra == "pymoo"
Provides-Extra: test
Requires-Dist: pytest; extra == "test"
Requires-Dist: pytest-cov; extra == "test"
Requires-Dist: requests; extra == "test"
Requires-Dist: pymoo; extra == "test"
Requires-Dist: pfns; extra == "test"
Provides-Extra: dev
Requires-Dist: botorch[test]; extra == "dev"
Requires-Dist: flake8; extra == "dev"
Requires-Dist: ufmt; extra == "dev"
Requires-Dist: flake8-docstrings; extra == "dev"
Requires-Dist: sphinx; extra == "dev"
Requires-Dist: sphinx-rtd-theme; extra == "dev"
Provides-Extra: tutorials
Requires-Dist: cma; extra == "tutorials"
Requires-Dist: jupyter; extra == "tutorials"
Requires-Dist: matplotlib; extra == "tutorials"
Requires-Dist: memory_profiler; extra == "tutorials"
Requires-Dist: papermill; extra == "tutorials"
Requires-Dist: pykeops; extra == "tutorials"
Requires-Dist: torchvision; extra == "tutorials"
Requires-Dist: mdformat; extra == "tutorials"
Requires-Dist: pandas; extra == "tutorials"
Requires-Dist: lxml; extra == "tutorials"
Requires-Dist: mdformat-myst; extra == "tutorials"
Requires-Dist: tabulate; extra == "tutorials"
Dynamic: license-file
